odoo/addons/l10n_fr_pos_caisse_ap_ip/README.rst
odoo/addons/l10n_fr_pos_caisse_ap_ip/__init__.py
odoo/addons/l10n_fr_pos_caisse_ap_ip/__manifest__.py
odoo/addons/l10n_fr_pos_caisse_ap_ip/i18n/es.po
odoo/addons/l10n_fr_pos_caisse_ap_ip/i18n/fr.po
odoo/addons/l10n_fr_pos_caisse_ap_ip/i18n/l10n_fr_pos_caisse_ap_ip.pot
odoo/addons/l10n_fr_pos_caisse_ap_ip/models/__init__.py
odoo/addons/l10n_fr_pos_caisse_ap_ip/models/pos_payment_method.py
odoo/addons/l10n_fr_pos_caisse_ap_ip/readme/CONFIGURE.md
odoo/addons/l10n_fr_pos_caisse_ap_ip/readme/CONTRIBUTORS.md
odoo/addons/l10n_fr_pos_caisse_ap_ip/readme/CREDITS.md
odoo/addons/l10n_fr_pos_caisse_ap_ip/readme/DESCRIPTION.md
odoo/addons/l10n_fr_pos_caisse_ap_ip/static/description/icon.png
odoo/addons/l10n_fr_pos_caisse_ap_ip/static/description/index.html
odoo/addons/l10n_fr_pos_caisse_ap_ip/static/src/app/utils/payment/payment_caisse_ap_ip.esm.js
odoo/addons/l10n_fr_pos_caisse_ap_ip/views/pos_payment_method.xml
odoo_addon_l10n_fr_pos_caisse_ap_ip-19.0.1.0.0.3.dist-info/METADATA
odoo_addon_l10n_fr_pos_caisse_ap_ip-19.0.1.0.0.3.dist-info/WHEEL
odoo_addon_l10n_fr_pos_caisse_ap_ip-19.0.1.0.0.3.dist-info/top_level.txt
odoo_addon_l10n_fr_pos_caisse_ap_ip-19.0.1.0.0.3.dist-info/RECORD
