Metadata-Version: 2.1
Name: odoo-addon-l10n_fr_pos_caisse_ap_ip
Version: 19.0.1.0.0.3
Requires-Dist: odoo==19.0.*
Summary: Add support for Caisse-AP payment protocol used in France
Home-page: https://github.com/OCA/l10n-france
License: AGPL-3
Author: Akretion,Odoo Community Association (OCA)
Author-email: support@odoo-community.org
Classifier: Programming Language :: Python
Classifier: Framework :: Odoo
Classifier: Framework :: Odoo :: 19.0
Classifier: License :: OSI Approved :: GNU Affero General Public License v3
